stackspot_commit/__init__.py
stackspot_commit/cli.py
stackspot_commit/commit_generator.py
stackspot_commit/commit_tool.py
stackspot_commit/config.py
stackspot_commit/git_handler.py
stackspot_commit/models.py
stackspot_commit/stackspot_service.py
stackspot_commit_helper-0.1.9.dist-info/licenses/LICENSE
stackspot_commit_helper-0.1.9.dist-info/METADATA
stackspot_commit_helper-0.1.9.dist-info/WHEEL
stackspot_commit_helper-0.1.9.dist-info/entry_points.txt
stackspot_commit_helper-0.1.9.dist-info/top_level.txt
stackspot_commit_helper-0.1.9.dist-info/RECORD
