Metadata-Version: 2.4
Name: stackspot-commit-helper
Version: 0.1.9
Summary: Auto-commit tool integrated with Stackspot AI
Author-email: Engeziellithon vieira <engeziellithonvieira@gmail.com>
License: MIT
Project-URL: Github page, https://github.com/engeziellithonzup/stackspot-commit-helper
Keywords: git,commit,stackspot,ai
Classifier: Programming Language :: Python :: 3
Classifier: License :: OSI Approved :: MIT License
Classifier: Operating System :: OS Independent
License-File: LICENSE
Requires-Dist: python-dotenv
Requires-Dist: stackspot
Dynamic: license-file
